mctmodule/__init__.py
mctmodule/db_conn.py
mctmodule/mct_dc.py
mctmodule/mct_err.py
mctmodule/mongo_conn.py
mctmodule-0.0.4.dist-info/METADATA
mctmodule-0.0.4.dist-info/WHEEL
mctmodule-0.0.4.dist-info/top_level.txt
mctmodule-0.0.4.dist-info/RECORD
